{
  "todos": [
    { "id": 1, "title": "Buy groceries for the week", "completed": false },
    { "id": 2, "title": "Finish reading 'Atomic Habits'", "completed": false },
    { "id": 3, "title": "Clean the living room", "completed": true },
    { "id": 4, "title": "Reply to work emails", "completed": true },
    { "id": 5, "title": "Plan the weekend trip", "completed": false },
    { "id": 6, "title": "Update LinkedIn profile", "completed": true },
    { "id": 7, "title": "Pay electricity bill", "completed": false },
    { "id": 8, "title": "Submit project report", "completed": false },
    { "id": 9, "title": "Book dentist appointment", "completed": true },
    { "id": 10, "title": "Water the plants", "completed": false },
    { "id": 11, "title": "Organize closet", "completed": false },
    { "id": 12, "title": "Research investment options", "completed": true },
    { "id": 13, "title": "Fix the kitchen sink", "completed": false },
    { "id": 14, "title": "Schedule car maintenance", "completed": false },
    {
      "id": 15,
      "title": "Write blog post on productivity",
      "completed": false
    },
    { "id": 16, "title": "Call parents to check in", "completed": true },
    { "id": 17, "title": "Update personal budget", "completed": false },
    { "id": 18, "title": "Prepare presentation slides", "completed": true },
    { "id": 19, "title": "Walk the dog", "completed": false },
    { "id": 20, "title": "Do laundry", "completed": true },
    { "id": 21, "title": "Go for a morning run", "completed": false },
    { "id": 22, "title": "Attend online webinar", "completed": true },
    { "id": 23, "title": "Complete coding challenge", "completed": false },
    { "id": 24, "title": "Buy a birthday gift for Sarah", "completed": false },
    { "id": 25, "title": "Refill prescription", "completed": true },
    { "id": 26, "title": "Update resume", "completed": false },
    { "id": 27, "title": "Clean the garage", "completed": false },
    { "id": 28, "title": "Meditate for 15 minutes", "completed": true },
    { "id": 29, "title": "Backup important files", "completed": false },
    { "id": 30, "title": "Buy new running shoes", "completed": false },
    { "id": 31, "title": "Attend yoga class", "completed": true },
    { "id": 32, "title": "Meal prep for the week", "completed": false },
    { "id": 33, "title": "Fix broken chair in the office", "completed": false },
    { "id": 34, "title": "Write a thank you note", "completed": true },
    { "id": 35, "title": "Prepare dinner for friends", "completed": false },
    { "id": 36, "title": "Plan next month's budget", "completed": false },
    { "id": 37, "title": "Read 'The Lean Startup'", "completed": true },
    { "id": 38, "title": "Clean out email inbox", "completed": false },
    {
      "id": 39,
      "title": "Finish organizing digital photos",
      "completed": false
    },
    { "id": 40, "title": "Sign up for photography class", "completed": true },
    { "id": 41, "title": "Pick up dry cleaning", "completed": false },
    { "id": 42, "title": "Buy new light bulbs", "completed": false },
    { "id": 43, "title": "Clean the bathroom", "completed": true },
    { "id": 44, "title": "Plan a date night", "completed": false },
    { "id": 45, "title": "Sign up for gym membership", "completed": true },
    { "id": 46, "title": "Create a monthly reading list", "completed": false },
    { "id": 47, "title": "Research travel destinations", "completed": true },
    { "id": 48, "title": "Renew car insurance", "completed": false },
    { "id": 49, "title": "Organize bookshelves", "completed": false },
    { "id": 50, "title": "Fix garden fence", "completed": true },
    { "id": 51, "title": "Study for final exam", "completed": false },
    { "id": 52, "title": "Take car for a wash", "completed": false },
    { "id": 53, "title": "Finish painting the guest room", "completed": true },
    { "id": 54, "title": "Research new phone plans", "completed": false },
    {
      "id": 55,
      "title": "Replace smoke detector batteries",
      "completed": true
    },
    { "id": 56, "title": "Call insurance company", "completed": false },
    { "id": 57, "title": "Refill the water filter", "completed": true },
    { "id": 58, "title": "Prepare for job interview", "completed": false },
    { "id": 59, "title": "Rearrange bedroom furniture", "completed": true },
    { "id": 60, "title": "Plan summer vacation", "completed": false },
    { "id": 61, "title": "Submit tax return", "completed": true },
    {
      "id": 62,
      "title": "Read 'Sapiens' by Yuval Noah Harari",
      "completed": false
    },
    {
      "id": 63,
      "title": "Organize receipts for expense report",
      "completed": false
    },
    { "id": 64, "title": "Install new app updates", "completed": true },
    { "id": 65, "title": "Write a short story", "completed": false },
    { "id": 66, "title": "Walk to the park", "completed": true },
    { "id": 67, "title": "Clean out the fridge", "completed": false },
    { "id": 68, "title": "Plan family reunion", "completed": true },
    { "id": 69, "title": "Watch new Netflix series", "completed": false },
    { "id": 70, "title": "Print vacation photos", "completed": true },
    { "id": 71, "title": "Clean out storage room", "completed": false },
    { "id": 72, "title": "Fix wobbly table leg", "completed": false },
    { "id": 73, "title": "Research new laptop options", "completed": true },
    { "id": 74, "title": "Donate unused clothes", "completed": false },
    { "id": 75, "title": "Plan a movie night with friends", "completed": true },
    { "id": 76, "title": "Repaint living room walls", "completed": false },
    { "id": 77, "title": "Fix leaky faucet", "completed": false },
    { "id": 78, "title": "Update security system", "completed": true },
    { "id": 79, "title": "Research online courses", "completed": false },
    { "id": 80, "title": "Prepare marketing report", "completed": true },
    { "id": 81, "title": "Call the plumber", "completed": false },
    { "id": 82, "title": "Set up new email filters", "completed": true },
    { "id": 83, "title": "Pick up prescription", "completed": false },
    { "id": 84, "title": "Organize holiday decorations", "completed": true },
    { "id": 85, "title": "Research new job opportunities", "completed": false },
    { "id": 86, "title": "Check credit card statement", "completed": true },
    { "id": 87, "title": "Replace old towels", "completed": false },
    { "id": 88, "title": "Send birthday card to cousin", "completed": true },
    {
      "id": 89,
      "title": "Create a backup of phone contacts",
      "completed": false
    },
    { "id": 90, "title": "Go hiking this weekend", "completed": true },
    { "id": 91, "title": "Find new recipes to try", "completed": false },
    { "id": 92, "title": "Schedule hair appointment", "completed": false },
    { "id": 93, "title": "Buy ingredients for dinner", "completed": true },
    { "id": 94, "title": "Refinish the kitchen cabinets", "completed": false },
    { "id": 95, "title": "Replace batteries in TV remote", "completed": true },
    { "id": 96, "title": "Wash the windows", "completed": false },
    { "id": 97, "title": "Organize photo albums", "completed": true },
    { "id": 98, "title": "Renew passport", "completed": false },
    { "id": 99, "title": "Read the latest tech news", "completed": true },
    { "id": 100, "title": "Write a cover letter", "completed": false }
  ]
}
